Metadata-Version: 2.1
Name: zappa-manage
Version: 0.0.3
Summary: Official Manage Package for edX Zappa Bots
Home-page: https://github.com/edx/zappa-manage
Author: edX-DevOps
Author-email: devops@edx.org
License: UNKNOWN
Platform: UNKNOWN
Classifier: Programming Language :: Python :: 3
Classifier: License :: OSI Approved :: MIT License
Classifier: Operating System :: OS Independent
Requires-Python: >=3.6
